README.rst
setup.cfg
setup.py
peek_storage/__init__.py
peek_storage/run_peek_storage.py
peek_storage/winsvc_peek_storage.py
peek_storage.egg-info/PKG-INFO
peek_storage.egg-info/SOURCES.txt
peek_storage.egg-info/dependency_links.txt
peek_storage.egg-info/entry_points.txt
peek_storage.egg-info/not-zip-safe
peek_storage.egg-info/requires.txt
peek_storage.egg-info/top_level.txt
peek_storage/_private/StorageInit.py
peek_storage/_private/__init__.py
peek_storage/_private/alembic.ini
peek_storage/_private/alembic/env.py
peek_storage/_private/alembic/script.py.mako
peek_storage/_private/alembic/versions/12a0ab3826f3_add_run_generic_python.py
peek_storage/_private/alembic/versions/2efc91c0f0f6_add_plpython3u.py
peek_storage/_private/alembic/versions/34490abd765c_add_pg_load_payload_tuples.py
peek_storage/_private/alembic/versions/51e48a6594d5_up1_run_generic_py.py
peek_storage/_private/alembic/versions/72518909970f_add_run_worker_plpy.py
peek_storage/_private/alembic/versions/__init__.py
peek_storage/_private/alembic/versions/bab14faf0cd7_add_timescale.py
peek_storage/_private/plugin/PeekStoragePlatformHook.py
peek_storage/_private/plugin/StoragePluginLoader.py
peek_storage/_private/plugin/StoragePluginLoaderTest.py
peek_storage/_private/plugin/__init__.py
peek_storage/_private/service/PeekStorageConfig.py
peek_storage/_private/service/StorageSiteResource.py
peek_storage/_private/service/__init__.py
peek_storage/_private/service/sw_download/PeekSwDownloadResource.py
peek_storage/_private/service/sw_download/PluginSwDownloadResource.py
peek_storage/_private/service/sw_download/__init__.py
peek_storage/_private/service/sw_install/PeekSwInstallManager.py
peek_storage/_private/service/sw_install/PluginSwInstallManager.py
peek_storage/_private/service/sw_install/__init__.py
peek_storage/_private/storage/DeclarativeBase.py
peek_storage/_private/storage/Setting.py
peek_storage/_private/storage/__init__.py
peek_storage/_private/test/StorageTestMixin.py
peek_storage/_private/test/__init__.py
peek_storage/plpython/LoadPayloadPgUtil.py
peek_storage/plpython/RunPyInPg.py
peek_storage/plpython/RunPyInPgTest.py
peek_storage/plpython/RunWorkerTaskPyInPg.py
peek_storage/plpython/__init__.py