Metadata-Version: 1.1
Name: peek-storage
Version: 2.4.1
Summary: Peek Platform - Server Service
Home-page: https://github.com/Synerty/peek-storage
Author: Synerty
Author-email: contact@synerty.com
License: UNKNOWN
Download-URL: https://github.com/Synerty/peek-storage/tarball/2.4.1
Keywords: Peek,Python,Platform,synerty
Platform: UNKNOWN
Classifier: Programming Language :: Python :: 3.5
